StruanAi/__init__.py
StruanAi/main.py
StruanAi-2.6.2.dist-info/LICENSE
StruanAi-2.6.2.dist-info/METADATA
StruanAi-2.6.2.dist-info/WHEEL
StruanAi-2.6.2.dist-info/top_level.txt
StruanAi-2.6.2.dist-info/RECORD
