Metadata-Version: 2.1
Name: StruanAi
Version: 2.6.2
Summary: For Makeing Ai Assistans Quicker To Make And Verry Easy To Use.
Home-page: https://github.com/StruanMclean/StruanAi
Author: StruanMclean
Author-email: StruanMclean28@gmail.com
License: UNKNOWN
Platform: UNKNOWN
Classifier: Programming Language :: Python :: 3
Classifier: License :: OSI Approved :: MIT License
Classifier: Operating System :: OS Independent
Requires-Python: >=3.7
